cinquis/__init__.py
cinquis/testcinquis.py
cinquis-0.0.2.dist-info/METADATA
cinquis-0.0.2.dist-info/WHEEL
cinquis-0.0.2.dist-info/licenses/LICENSE
cinquis-0.0.2.dist-info/RECORD
